raa/__init__.py
raa/module.py
raa-0.0.1.dist-info/LICENSE
raa-0.0.1.dist-info/METADATA
raa-0.0.1.dist-info/WHEEL
raa-0.0.1.dist-info/top_level.txt
raa-0.0.1.dist-info/RECORD
