Metadata-Version: 2.1
Name: raa
Version: 0.0.1
Summary: A small example package
Home-page: https://github.com/raincoder87/lumache
Author: Mahmoud Hefny
Author-email: hefnymah@gmail.com
License: UNKNOWN
Project-URL: Bug Tracker, https://github.com/raincoder87/lumache/issues
Platform: UNKNOWN
Classifier: Programming Language :: Python :: 3
Classifier: License :: OSI Approved :: MIT License
Classifier: Operating System :: OS Independent
Requires-Python: >=3.6
License-File: LICENSE
